yg_token/__init__.py
yg_token/yg_token.py
yg_token-1.0.dist-info/LICENSE
yg_token-1.0.dist-info/METADATA
yg_token-1.0.dist-info/WHEEL
yg_token-1.0.dist-info/top_level.txt
yg_token-1.0.dist-info/RECORD
