Metadata-Version: 2.1
Name: yg-token
Version: 1.0
Summary: 能生成JWT的python3工具
Home-page: https://github.com/BeyondLam
Author: 好音宫
Author-email: admin@jamkung.com
License: MIT Licence
Keywords: pip,token,json_web_token,JWT
Platform: any
Requires-Python: >=3
